postfinancecheckout/__init__.py
postfinancecheckout/api_client.py
postfinancecheckout/configuration.py
postfinancecheckout/rest.py
postfinancecheckout/api/__init__.py
postfinancecheckout/api/account_service_api.py
postfinancecheckout/api/application_user_service_api.py
postfinancecheckout/api/bank_account_service_api.py
postfinancecheckout/api/bank_transaction_service_api.py
postfinancecheckout/api/charge_attempt_service_api.py
postfinancecheckout/api/charge_bank_transaction_service_api.py
postfinancecheckout/api/charge_flow_level_payment_link_service_api.py
postfinancecheckout/api/charge_flow_level_service_api.py
postfinancecheckout/api/charge_flow_service_api.py
postfinancecheckout/api/condition_type_service_api.py
postfinancecheckout/api/country_service_api.py
postfinancecheckout/api/country_state_service_api.py
postfinancecheckout/api/currency_bank_account_service_api.py
postfinancecheckout/api/currency_service_api.py
postfinancecheckout/api/customer_address_service_api.py
postfinancecheckout/api/customer_comment_service_api.py
postfinancecheckout/api/customer_service_api.py
postfinancecheckout/api/delivery_indication_service_api.py
postfinancecheckout/api/document_template_service_api.py
postfinancecheckout/api/document_template_type_service_api.py
postfinancecheckout/api/external_transfer_bank_transaction_service_api.py
postfinancecheckout/api/human_user_service_api.py
postfinancecheckout/api/internal_transfer_bank_transaction_service_api.py
postfinancecheckout/api/invoice_reconciliation_record_service_api.py
postfinancecheckout/api/invoice_reimbursement_service_api.py
postfinancecheckout/api/label_description_group_service_api.py
postfinancecheckout/api/label_description_service_api.py
postfinancecheckout/api/language_service_api.py
postfinancecheckout/api/legal_organization_form_service_api.py
postfinancecheckout/api/manual_task_service_api.py
postfinancecheckout/api/payment_connector_configuration_service_api.py
postfinancecheckout-3.0.3.dist-info/LICENSE
postfinancecheckout-3.0.3.dist-info/METADATA
postfinancecheckout-3.0.3.dist-info/WHEEL
postfinancecheckout-3.0.3.dist-info/top_level.txt
postfinancecheckout-3.0.3.dist-info/RECORD
