Metadata-Version: 2.1
Name: postfinancecheckout
Version: 3.0.3
Summary: SDK that allows you to access PostFinance Checkout
Home-page: UNKNOWN
Author: Wallee AG
License: Apache-2.0
Keywords: postfinancecheckout,Payment,Payment Integration
Platform: UNKNOWN
Classifier: Intended Audience :: Developers
Classifier: Intended Audience :: Financial and Insurance Industry
Classifier: License :: OSI Approved :: Apache Software License
Classifier: Natural Language :: English
Classifier: Operating System :: OS Independent
Classifier: Programming Language :: Python :: 3
Classifier: Programming Language :: Python :: 3.5
Classifier: Programming Language :: Python :: 3.6
Classifier: Programming Language :: Python :: 3.7
Classifier: Programming Language :: Python :: 3.8
Classifier: Programming Language :: Python :: 3.9
Classifier: Topic :: Office/Business :: Financial :: Point-Of-Sale
Requires-Python: >=3.5
License-File: LICENSE
Requires-Dist: certifi (>=2017.4.17)
Requires-Dist: python-dateutil (>=2.1)
Requires-Dist: six (>=1.10)
Requires-Dist: urllib3 (>=1.23)
